<?xml version = '1.0' encoding = 'UTF-8'?>
<Relation class="oracle.dbtools.crest.model.design.logical.Relation" name="Relation_75" directorySegmentName="seg_0" id="9AD18D26-778B-A13E-447C-7E9C124478B4">
<createdBy>filip</createdBy>
<createdTime>2019-12-16 14:36:53 UTC</createdTime>
<ownerDesignName>Main</ownerDesignName>
<sourcePk>8EEBEB25-E459-234E-3058-4AC3BBCD7088</sourcePk>
<identifying>false</identifying>
<optionalSource>true</optionalSource>
<optionalTarget>false</optionalTarget>
<sourceCardinality>1</sourceCardinality>
<sourceEntity>628A420B-B313-E0CF-2C96-19F047FB9DD2</sourceEntity>
<targetCardinalityString>*</targetCardinalityString>
<targetEntity>6266FC71-1249-8971-A981-C1E606A95B41</targetEntity>
<transferable>true</transferable>
<deleteRule>NO ACTION</deleteRule>
</Relation>